flywheel/__init__.py
flywheel/compat.py
flywheel/engine.py
flywheel/model_meta.py
flywheel/models.py
flywheel/query.py
flywheel/tests.py
flywheel/fields/__init__.py
flywheel/fields/conditions.py
flywheel/fields/indexes.py
flywheel/fields/types.py
flywheel-0.5.4.dist-info/LICENSE
flywheel-0.5.4.dist-info/METADATA
flywheel-0.5.4.dist-info/WHEEL
flywheel-0.5.4.dist-info/top_level.txt
flywheel-0.5.4.dist-info/RECORD
