Metadata-Version: 2.1
Name: flywheel
Version: 0.5.4
Summary: SQLAlchemy-style ORM for Amazon's DynamoDB
Home-page: http://flywheel.readthedocs.org/
Author: Steven Arcangeli
Author-email: stevearc@stevearc.com
License: MIT
Keywords: aws dynamo dynamodb orm odm
Platform: any
Classifier: Development Status :: 4 - Beta
Classifier: Intended Audience :: Developers
Classifier: License :: OSI Approved :: MIT License
Classifier: Operating System :: OS Independent
Classifier: Programming Language :: Python
Classifier: Programming Language :: Python :: 2
Classifier: Programming Language :: Python :: 2.7
Classifier: Programming Language :: Python :: 3
Classifier: Programming Language :: Python :: 3.4
Classifier: Programming Language :: Python :: 3.5
Classifier: Programming Language :: Python :: 3.6
Classifier: Topic :: Database
Requires-Dist: dynamo3 (<1.0,>=0.4.9)
Requires-Dist: six
